juicefs_client/__init__.py
juicefs_client/__main__.py
juicefs_client/client.py
juicefs_client-0.1.12.dist-info/LICENSE
juicefs_client-0.1.12.dist-info/METADATA
juicefs_client-0.1.12.dist-info/WHEEL
juicefs_client-0.1.12.dist-info/top_level.txt
juicefs_client-0.1.12.dist-info/RECORD
