Metadata-Version: 2.1
Name: juicefs-client
Version: 0.1.12
Summary: A Python client for JuiceFS operations
Home-page: https://github.com/yourusername/juicefs-client
Author: Luke
Author-email: Luke <pypi@luke.archi>
License: MIT License
Project-URL: Homepage, https://github.com/yourusername/juicefs-client
Keywords: juicefs,storage,cloud
Classifier: License :: OSI Approved :: MIT License
Classifier: Programming Language :: Python
Classifier: Programming Language :: Python :: 3
Requires-Python: >=3.7
License-File: LICENSE
